{
  "annotations": {
    "list": [
      {
        "builtIn": 1,
        "datasource": {
          "type": "grafana",
          "uid": "-- Grafana --"
        },
        "enable": true,
        "hide": true,
        "iconColor": "rgba(0, 211, 255, 1)",
        "name": "Annotations & Alerts",
        "target": {
          "limit": 100,
          "matchAny": false,
          "tags": [],
          "type": "dashboard"
        },
        "type": "dashboard"
      }
    ]
  },
  "description": "OCP Virt related performance metrics",
  "editable": true,
  "fiscalYearStartMonth": 0,
  "graphTooltip": 0,
  "id": 19,
  "links": [],
  "liveNow": false,
  "panels": [
    {
      "collapsed": true,
      "gridPos": {
        "h": 1,
        "w": 24,
        "x": 0,
        "y": 0
      },
      "id": 6,
      "panels": [
        {
          "datasource": {
            "type": "prometheus",
            "uid": "PF55DCC5EC58ABF5A"
          },
          "fieldConfig": {
            "defaults": {
              "color": {
                "mode": "thresholds"
              },
              "mappings": [
                {
                  "options": {
                    "0": {
                      "color": "green",
                      "index": 0,
                      "text": "Heathly"
                    },
                    "1": {
                      "color": "red",
                      "index": 1,
                      "text": "Warning"
                    },
                    "2": {
                      "color": "dark-red",
                      "index": 2,
                      "text": "Error"
                    }
                  },
                  "type": "value"
                }
              ],
              "thresholds": {
                "mode": "absolute",
                "steps": [
                  {
                    "color": "green",
                    "value": null
                  },
                  {
                    "color": "red",
                    "value": 80
                  }
                ]
              }
            },
            "overrides": []
          },
          "gridPos": {
            "h": 3,
            "w": 2,
            "x": 0,
            "y": 1
          },
          "id": 30,
          "options": {
            "colorMode": "value",
            "graphMode": "none",
            "justifyMode": "auto",
            "orientation": "auto",
            "reduceOptions": {
              "calcs": [
                "lastNotNull"
              ],
              "fields": "",
              "values": false
            },
            "textMode": "auto"
          },
          "pluginVersion": "9.4.3",
          "targets": [
            {
              "datasource": {
                "type": "prometheus",
                "uid": "PF55DCC5EC58ABF5A"
              },
              "editorMode": "code",
              "expr": "kubevirt_hco_system_health_status",
              "legendFormat": "__auto",
              "range": true,
              "refId": "A"
            }
          ],
          "title": "HCO System",
          "type": "stat"
        },
        {
          "datasource": {
            "type": "prometheus",
            "uid": "PF55DCC5EC58ABF5A"
          },
          "fieldConfig": {
            "defaults": {
              "color": {
                "mode": "thresholds"
              },
              "mappings": [
                {
                  "options": {
                    "0": {
                      "color": "green",
                      "index": 0,
                      "text": "Healthy"
                    },
                    "1": {
                      "color": "red",
                      "index": 1,
                      "text": "Warning"
                    },
                    "2": {
                      "color": "dark-red",
                      "index": 2,
                      "text": "Critical"
                    }
                  },
                  "type": "value"
                }
              ],
              "thresholds": {
                "mode": "absolute",
                "steps": [
                  {
                    "color": "green",
                    "value": null
                  },
                  {
                    "color": "red",
                    "value": 80
                  }
                ]
              }
            },
            "overrides": []
          },
          "gridPos": {
            "h": 3,
            "w": 2,
            "x": 2,
            "y": 1
          },
          "id": 26,
          "options": {
            "colorMode": "value",
            "graphMode": "none",
            "justifyMode": "auto",
            "orientation": "auto",
            "reduceOptions": {
              "calcs": [
                "lastNotNull"
              ],
              "fields": "",
              "values": false
            },
            "textMode": "auto"
          },
          "pluginVersion": "9.4.3",
          "targets": [
            {
              "datasource": {
                "type": "prometheus",
                "uid": "PF55DCC5EC58ABF5A"
              },
              "editorMode": "code",
              "expr": "kubevirt_hyperconverged_operator_health_status{}",
              "legendFormat": "__auto",
              "range": true,
              "refId": "A"
            }
          ],
          "title": "HCO Operator",
          "type": "stat"
        },
        {
          "datasource": {
            "type": "prometheus",
            "uid": "PF55DCC5EC58ABF5A"
          },
          "description": "The total number of VMs that's being created. Including non-running VMs",
          "fieldConfig": {
            "defaults": {
              "color": {
                "fixedColor": "green",
                "mode": "fixed"
              },
              "mappings": [],
              "noValue": "0",
              "thresholds": {
                "mode": "absolute",
                "steps": [
                  {
                    "color": "green",
                    "value": null
                  },
                  {
                    "color": "red",
                    "value": 80
                  }
                ]
              }
            },
            "overrides": []
          },
          "gridPos": {
            "h": 3,
            "w": 2,
            "x": 4,
            "y": 1
          },
          "id": 24,
          "options": {
            "colorMode": "value",
            "graphMode": "none",
            "justifyMode": "auto",
            "orientation": "auto",
            "reduceOptions": {
              "calcs": [
                "lastNotNull"
              ],
              "fields": "",
              "values": false
            },
            "text": {},
            "textMode": "auto"
          },
          "pluginVersion": "9.4.3",
          "targets": [
            {
              "datasource": {
                "type": "prometheus",
                "uid": "PF55DCC5EC58ABF5A"
              },
              "editorMode": "code",
              "expr": "sum(kubevirt_number_of_vms)",
              "legendFormat": "__auto",
              "range": true,
              "refId": "A"
            }
          ],
          "title": "Created VMs",
          "type": "stat"
        },
        {
          "datasource": {
            "type": "prometheus",
            "uid": "PF55DCC5EC58ABF5A"
          },
          "fieldConfig": {
            "defaults": {
              "color": {
                "fixedColor": "green",
                "mode": "fixed"
              },
              "mappings": [],
              "thresholds": {
                "mode": "absolute",
                "steps": [
                  {
                    "color": "green",
                    "value": null
                  },
                  {
                    "color": "red",
                    "value": 80
                  }
                ]
              }
            },
            "overrides": []
          },
          "gridPos": {
            "h": 3,
            "w": 2,
            "x": 6,
            "y": 1
          },
          "id": 38,
          "options": {
            "colorMode": "value",
            "graphMode": "none",
            "justifyMode": "auto",
            "orientation": "auto",
            "reduceOptions": {
              "calcs": [
                "lastNotNull"
              ],
              "fields": "",
              "values": false
            },
            "textMode": "auto"
          },
          "pluginVersion": "9.4.3",
          "targets": [
            {
              "datasource": {
                "type": "prometheus",
                "uid": "PF55DCC5EC58ABF5A"
              },
              "editorMode": "code",
              "expr": "sum(cnv:vmi_status_running:count)",
              "legendFormat": "__auto",
              "range": true,
              "refId": "A"
            }
          ],
          "title": "Running VMs",
          "type": "stat"
        },
        {
          "datasource": {
            "type": "prometheus",
            "uid": "PF55DCC5EC58ABF5A"
          },
          "description": "The sum of all VM's CPU request",
          "fieldConfig": {
            "defaults": {
              "color": {
                "fixedColor": "green",
                "mode": "fixed"
              },
              "mappings": [],
              "thresholds": {
                "mode": "absolute",
                "steps": [
                  {
                    "color": "green",
                    "value": null
                  },
                  {
                    "color": "red",
                    "value": 80
                  }
                ]
              }
            },
            "overrides": []
          },
          "gridPos": {
            "h": 3,
            "w": 2,
            "x": 8,
            "y": 1
          },
          "id": 28,
          "options": {
            "colorMode": "value",
            "graphMode": "none",
            "justifyMode": "auto",
            "orientation": "auto",
            "reduceOptions": {
              "calcs": [
                "lastNotNull"
              ],
              "fields": "",
              "values": false
            },
            "textMode": "auto"
          },
          "pluginVersion": "9.4.3",
          "targets": [
            {
              "datasource": {
                "type": "prometheus",
                "uid": "PF55DCC5EC58ABF5A"
              },
              "editorMode": "code",
              "expr": "cluster:vmi_request_cpu_cores:sum",
              "legendFormat": "__auto",
              "range": true,
              "refId": "A"
            }
          ],
          "title": "Total CPU Request ",
          "type": "stat"
        },
        {
          "datasource": {
            "type": "prometheus",
            "uid": "PF55DCC5EC58ABF5A"
          },
          "description": "The sum of all VM's RAM request",
          "fieldConfig": {
            "defaults": {
              "color": {
                "fixedColor": "green",
                "mode": "fixed"
              },
              "mappings": [],
              "thresholds": {
                "mode": "absolute",
                "steps": [
                  {
                    "color": "green",
                    "value": null
                  },
                  {
                    "color": "red",
                    "value": 80
                  }
                ]
              },
              "unit": "decbytes"
            },
            "overrides": []
          },
          "gridPos": {
            "h": 3,
            "w": 3,
            "x": 10,
            "y": 1
          },
          "id": 32,
          "options": {
            "colorMode": "value",
            "graphMode": "none",
            "justifyMode": "auto",
            "orientation": "auto",
            "reduceOptions": {
              "calcs": [
                "lastNotNull"
              ],
              "fields": "",
              "values": false
            },
            "textMode": "auto"
          },
          "pluginVersion": "9.4.3",
          "targets": [
            {
              "datasource": {
                "type": "prometheus",
                "uid": "PF55DCC5EC58ABF5A"
              },
              "editorMode": "code",
              "expr": "sum(kubevirt_vm_resource_requests)",
              "legendFormat": "__auto",
              "range": true,
              "refId": "A"
            }
          ],
          "title": "Total RAM Request",
          "type": "stat"
        },
        {
          "datasource": {
            "type": "prometheus",
            "uid": "PF55DCC5EC58ABF5A"
          },
          "fieldConfig": {
            "defaults": {
              "color": {
                "fixedColor": "green",
                "mode": "fixed"
              },
              "mappings": [],
              "thresholds": {
                "mode": "absolute",
                "steps": [
                  {
                    "color": "green",
                    "value": null
                  },
                  {
                    "color": "red",
                    "value": 80
                  }
                ]
              }
            },
            "overrides": []
          },
          "gridPos": {
            "h": 3,
            "w": 2,
            "x": 13,
            "y": 1
          },
          "id": 36,
          "options": {
            "colorMode": "value",
            "graphMode": "none",
            "justifyMode": "auto",
            "orientation": "auto",
            "reduceOptions": {
              "calcs": [
                "lastNotNull"
              ],
              "fields": "",
              "values": false
            },
            "textMode": "auto"
          },
          "pluginVersion": "9.4.3",
          "targets": [
            {
              "datasource": {
                "type": "prometheus",
                "uid": "PF55DCC5EC58ABF5A"
              },
              "editorMode": "code",
              "expr": "kubevirt_virt_api_up",
              "legendFormat": "__auto",
              "range": true,
              "refId": "A"
            }
          ],
          "title": "Virt API Pod Count",
          "type": "stat"
        },
        {
          "datasource": {
            "type": "prometheus",
            "uid": "PF55DCC5EC58ABF5A"
          },
          "description": "The delta between the pod with highest memory working set or rss and its requested memory for each container, virt-controller, virt-handler, virt-api and virt-operator. ",
          "fieldConfig": {
            "defaults": {
              "color": {
                "fixedColor": "green",
                "mode": "fixed"
              },
              "mappings": [],
              "thresholds": {
                "mode": "absolute",
                "steps": [
                  {
                    "color": "green",
                    "value": null
                  },
                  {
                    "color": "red",
                    "value": 80
                  }
                ]
              },
              "unit": "bytes"
            },
            "overrides": []
          },
          "gridPos": {
            "h": 3,
            "w": 4,
            "x": 15,
            "y": 1
          },
          "id": 34,
          "options": {
            "colorMode": "value",
            "graphMode": "none",
            "justifyMode": "auto",
            "orientation": "auto",
            "reduceOptions": {
              "calcs": [
                "lastNotNull"
              ],
              "fields": "",
              "values": false
            },
            "textMode": "auto"
          },
          "pluginVersion": "9.4.3",
          "targets": [
            {
              "datasource": {
                "type": "prometheus",
                "uid": "PF55DCC5EC58ABF5A"
              },
              "editorMode": "code",
              "expr": "sum(kubevirt_memory_delta_from_requested_bytes) ",
              "legendFormat": "__auto",
              "range": true,
              "refId": "A"
            }
          ],
          "title": "System Pod Memory Usage/Request Delta ",
          "type": "stat"
        },
        {
          "datasource": {
            "type": "prometheus",
            "uid": "PF55DCC5EC58ABF5A"
          },
          "description": "Average memory overhead per VM - The estimation of the memory amount required for virt-launcher’s infrastructure components (e.g. libvirt, QEMU)",
          "fieldConfig": {
            "defaults": {
              "color": {
                "fixedColor": "green",
                "mode": "fixed"
              },
              "mappings": [],
              "thresholds": {
                "mode": "absolute",
                "steps": [
                  {
                    "color": "green",
                    "value": null
                  },
                  {
                    "color": "red",
                    "value": 80
                  }
                ]
              },
              "unit": "bytes"
            },
            "overrides": []
          },
          "gridPos": {
            "h": 3,
            "w": 3,
            "x": 19,
            "y": 1
          },
          "id": 43,
          "options": {
            "colorMode": "value",
            "graphMode": "none",
            "justifyMode": "auto",
            "orientation": "auto",
            "reduceOptions": {
              "calcs": [
                "lastNotNull"
              ],
              "fields": "",
              "values": false
            },
            "textMode": "auto"
          },
          "pluginVersion": "9.4.3",
          "targets": [
            {
              "datasource": {
                "type": "prometheus",
                "uid": "PF55DCC5EC58ABF5A"
              },
              "editorMode": "code",
              "expr": "sum(kubevirt_vmi_launcher_memory_overhead_bytes{}) / count (kubevirt_vmi_launcher_memory_overhead_bytes{})",
              "legendFormat": "{{vmi}}",
              "range": true,
              "refId": "A"
            }
          ],
          "title": "Avg Virt Launcher Memory Overhead",
          "type": "stat"
        },
        {
          "datasource": {
            "type": "prometheus",
            "uid": "PF55DCC5EC58ABF5A"
          },
          "fieldConfig": {
            "defaults": {
              "color": {
                "fixedColor": "green",
                "mode": "fixed"
              },
              "custom": {
                "axisCenteredZero": false,
                "axisColorMode": "text",
                "axisLabel": "",
                "axisPlacement": "auto",
                "barAlignment": 0,
                "drawStyle": "line",
                "fillOpacity": 0,
                "gradientMode": "none",
                "hideFrom": {
                  "legend": false,
                  "tooltip": false,
                  "viz": false
                },
                "lineInterpolation": "linear",
                "lineWidth": 1,
                "pointSize": 5,
                "scaleDistribution": {
                  "type": "linear"
                },
                "showPoints": "auto",
                "spanNulls": false,
                "stacking": {
                  "group": "A",
                  "mode": "none"
                },
                "thresholdsStyle": {
                  "mode": "off"
                }
              },
              "mappings": [],
              "thresholds": {
                "mode": "absolute",
                "steps": [
                  {
                    "color": "green",
                    "value": null
                  },
                  {
                    "color": "red",
                    "value": 80
                  }
                ]
              },
              "unit": "bytes"
            },
            "overrides": []
          },
          "gridPos": {
            "h": 8,
            "w": 12,
            "x": 0,
            "y": 4
          },
          "id": 52,
          "options": {
            "legend": {
              "calcs": [
                "min",
                "max"
              ],
              "displayMode": "table",
              "placement": "bottom",
              "showLegend": true,
              "sortBy": "Max",
              "sortDesc": true
            },
            "tooltip": {
              "mode": "single",
              "sort": "none"
            }
          },
          "targets": [
            {
              "datasource": {
                "type": "prometheus",
                "uid": "PF55DCC5EC58ABF5A"
              },
              "editorMode": "code",
              "expr": "sum(container_memory_rss{pod!~\"virt-launcher.*\", namespace=\"openshift-cnv\" }) by (pod)",
              "legendFormat": "{{vmi}}",
              "range": true,
              "refId": "A"
            }
          ],
          "title": "CNV System Pod Memory Usage",
          "type": "timeseries"
        },
        {
          "datasource": {
            "type": "prometheus",
            "uid": "PF55DCC5EC58ABF5A"
          },
          "fieldConfig": {
            "defaults": {
              "color": {
                "fixedColor": "green",
                "mode": "fixed"
              },
              "custom": {
                "axisCenteredZero": false,
                "axisColorMode": "text",
                "axisLabel": "",
                "axisPlacement": "auto",
                "barAlignment": 0,
                "drawStyle": "line",
                "fillOpacity": 0,
                "gradientMode": "none",
                "hideFrom": {
                  "legend": false,
                  "tooltip": false,
                  "viz": false
                },
                "lineInterpolation": "linear",
                "lineWidth": 1,
                "pointSize": 5,
                "scaleDistribution": {
                  "type": "linear"
                },
                "showPoints": "auto",
                "spanNulls": false,
                "stacking": {
                  "group": "A",
                  "mode": "none"
                },
                "thresholdsStyle": {
                  "mode": "off"
                }
              },
              "mappings": [],
              "thresholds": {
                "mode": "absolute",
                "steps": [
                  {
                    "color": "green",
                    "value": null
                  },
                  {
                    "color": "red",
                    "value": 80
                  }
                ]
              },
              "unit": "percentunit"
            },
            "overrides": []
          },
          "gridPos": {
            "h": 8,
            "w": 12,
            "x": 12,
            "y": 4
          },
          "id": 51,
          "options": {
            "legend": {
              "calcs": [
                "min",
                "max"
              ],
              "displayMode": "table",
              "placement": "bottom",
              "showLegend": true,
              "sortBy": "Max",
              "sortDesc": true
            },
            "tooltip": {
              "mode": "single",
              "sort": "none"
            }
          },
          "targets": [
            {
              "datasource": {
                "type": "prometheus",
                "uid": "PF55DCC5EC58ABF5A"
              },
              "editorMode": "code",
              "expr": "sum(rate(container_cpu_usage_seconds_total{pod!~\"virt-launcher.*\", namespace=\"openshift-cnv\"}[1m])) by (pod)",
              "legendFormat": "{{vmi}}",
              "range": true,
              "refId": "A"
            }
          ],
          "title": "CNV System Pod CPU Usage",
          "type": "timeseries"
        },
        {
          "datasource": {
            "type": "prometheus",
            "uid": "PF55DCC5EC58ABF5A"
          },
          "fieldConfig": {
            "defaults": {
              "color": {
                "fixedColor": "green",
                "mode": "fixed"
              },
              "custom": {
                "axisCenteredZero": false,
                "axisColorMode": "text",
                "axisLabel": "",
                "axisPlacement": "auto",
                "barAlignment": 0,
                "drawStyle": "line",
                "fillOpacity": 0,
                "gradientMode": "none",
                "hideFrom": {
                  "legend": false,
                  "tooltip": false,
                  "viz": false
                },
                "lineInterpolation": "linear",
                "lineWidth": 1,
                "pointSize": 5,
                "scaleDistribution": {
                  "type": "linear"
                },
                "showPoints": "auto",
                "spanNulls": false,
                "stacking": {
                  "group": "A",
                  "mode": "none"
                },
                "thresholdsStyle": {
                  "mode": "off"
                }
              },
              "mappings": [],
              "thresholds": {
                "mode": "absolute",
                "steps": [
                  {
                    "color": "green",
                    "value": null
                  },
                  {
                    "color": "red",
                    "value": 80
                  }
                ]
              },
              "unit": "bytes"
            },
            "overrides": []
          },
          "gridPos": {
            "h": 8,
            "w": 12,
            "x": 0,
            "y": 12
          },
          "id": 40,
          "options": {
            "legend": {
              "calcs": [
                "min",
                "max"
              ],
              "displayMode": "table",
              "placement": "bottom",
              "showLegend": true,
              "sortBy": "Max",
              "sortDesc": true
            },
            "tooltip": {
              "mode": "single",
              "sort": "none"
            }
          },
          "targets": [
            {
              "datasource": {
                "type": "prometheus",
                "uid": "PF55DCC5EC58ABF5A"
              },
              "editorMode": "code",
              "expr": "label_replace(sum(container_memory_rss{pod=~\"virt-launcher.*\"}) by (pod), \"vmi\", \"$1\", \"pod\", \"virt-launcher-(.*)-[^-]+$\")",
              "legendFormat": "{{vmi}}",
              "range": true,
              "refId": "A"
            }
          ],
          "title": "VM Memory Usage",
          "type": "timeseries"
        },
        {
          "datasource": {
            "type": "prometheus",
            "uid": "PF55DCC5EC58ABF5A"
          },
          "fieldConfig": {
            "defaults": {
              "color": {
                "fixedColor": "green",
                "mode": "fixed"
              },
              "custom": {
                "axisCenteredZero": false,
                "axisColorMode": "text",
                "axisLabel": "",
                "axisPlacement": "auto",
                "barAlignment": 0,
                "drawStyle": "line",
                "fillOpacity": 0,
                "gradientMode": "none",
                "hideFrom": {
                  "legend": false,
                  "tooltip": false,
                  "viz": false
                },
                "lineInterpolation": "linear",
                "lineWidth": 1,
                "pointSize": 5,
                "scaleDistribution": {
                  "type": "linear"
                },
                "showPoints": "auto",
                "spanNulls": false,
                "stacking": {
                  "group": "A",
                  "mode": "none"
                },
                "thresholdsStyle": {
                  "mode": "off"
                }
              },
              "mappings": [],
              "thresholds": {
                "mode": "absolute",
                "steps": [
                  {
                    "color": "green",
                    "value": null
                  },
                  {
                    "color": "red",
                    "value": 80
                  }
                ]
              },
              "unit": "percentunit"
            },
            "overrides": []
          },
          "gridPos": {
            "h": 8,
            "w": 12,
            "x": 12,
            "y": 12
          },
          "id": 42,
          "options": {
            "legend": {
              "calcs": [
                "min",
                "max"
              ],
              "displayMode": "table",
              "placement": "bottom",
              "showLegend": true
            },
            "tooltip": {
              "mode": "single",
              "sort": "none"
            }
          },
          "targets": [
            {
              "datasource": {
                "type": "prometheus",
                "uid": "PF55DCC5EC58ABF5A"
              },
              "editorMode": "code",
              "expr": "label_replace(sum(rate(container_cpu_usage_seconds_total{pod=~\"virt-launcher.*\"}[1m])) by (pod),\"vmi\", \"$1\", \"pod\", \"virt-launcher-(.*)-[^-]+$\")",
              "legendFormat": "{{vmi}}",
              "range": true,
              "refId": "A"
            }
          ],
          "title": "VM CPU Usage",
          "type": "timeseries"
        },
        {
          "datasource": {
            "type": "prometheus",
            "uid": "PF55DCC5EC58ABF5A"
          },
          "description": "The percentage of avaiable memory listed by node",
          "fieldConfig": {
            "defaults": {
              "color": {
                "fixedColor": "green",
                "mode": "fixed"
              },
              "custom": {
                "axisCenteredZero": false,
                "axisColorMode": "text",
                "axisLabel": "",
                "axisPlacement": "auto",
                "barAlignment": 0,
                "drawStyle": "line",
                "fillOpacity": 0,
                "gradientMode": "none",
                "hideFrom": {
                  "legend": false,
                  "tooltip": false,
                  "viz": false
                },
                "lineInterpolation": "linear",
                "lineWidth": 1,
                "pointSize": 5,
                "scaleDistribution": {
                  "type": "linear"
                },
                "showPoints": "auto",
                "spanNulls": false,
                "stacking": {
                  "group": "A",
                  "mode": "none"
                },
                "thresholdsStyle": {
                  "mode": "off"
                }
              },
              "mappings": [],
              "thresholds": {
                "mode": "absolute",
                "steps": [
                  {
                    "color": "green",
                    "value": null
                  },
                  {
                    "color": "red",
                    "value": 80
                  }
                ]
              },
              "unit": "percentunit"
            },
            "overrides": []
          },
          "gridPos": {
            "h": 8,
            "w": 12,
            "x": 0,
            "y": 20
          },
          "id": 54,
          "options": {
            "legend": {
              "calcs": [
                "min",
                "max"
              ],
              "displayMode": "table",
              "placement": "bottom",
              "showLegend": true,
              "sortBy": "Max",
              "sortDesc": false
            },
            "tooltip": {
              "mode": "single",
              "sort": "none"
            }
          },
          "targets": [
            {
              "datasource": {
                "type": "prometheus",
                "uid": "PF55DCC5EC58ABF5A"
              },
              "editorMode": "code",
              "expr": "sum(node_memory_MemAvailable_bytes{}) by (instance) / sum(node_memory_MemTotal_bytes{}) by (instance) ",
              "legendFormat": "__auto",
              "range": true,
              "refId": "A"
            }
          ],
          "title": "Node Available Memory Pecentage",
          "type": "timeseries"
        },
        {
          "datasource": {
            "type": "prometheus",
            "uid": "PF55DCC5EC58ABF5A"
          },
          "fieldConfig": {
            "defaults": {
              "color": {
                "fixedColor": "green",
                "mode": "fixed"
              },
              "custom": {
                "axisCenteredZero": false,
                "axisColorMode": "text",
                "axisLabel": "",
                "axisPlacement": "auto",
                "barAlignment": 0,
                "drawStyle": "line",
                "fillOpacity": 0,
                "gradientMode": "none",
                "hideFrom": {
                  "legend": false,
                  "tooltip": false,
                  "viz": false
                },
                "lineInterpolation": "linear",
                "lineWidth": 1,
                "pointSize": 5,
                "scaleDistribution": {
                  "type": "linear"
                },
                "showPoints": "auto",
                "spanNulls": false,
                "stacking": {
                  "group": "A",
                  "mode": "none"
                },
                "thresholdsStyle": {
                  "mode": "off"
                }
              },
              "mappings": [],
              "thresholds": {
                "mode": "absolute",
                "steps": [
                  {
                    "color": "green",
                    "value": null
                  },
                  {
                    "color": "red",
                    "value": 80
                  }
                ]
              },
              "unit": "percentunit"
            },
            "overrides": []
          },
          "gridPos": {
            "h": 8,
            "w": 12,
            "x": 12,
            "y": 20
          },
          "id": 53,
          "options": {
            "legend": {
              "calcs": [
                "min",
                "max"
              ],
              "displayMode": "table",
              "placement": "bottom",
              "showLegend": true,
              "sortBy": "Max",
              "sortDesc": true
            },
            "tooltip": {
              "mode": "single",
              "sort": "none"
            }
          },
          "targets": [
            {
              "datasource": {
                "type": "prometheus",
                "uid": "PF55DCC5EC58ABF5A"
              },
              "editorMode": "code",
              "expr": "sum(rate(node_cpu_seconds_total{mode!=\"idle\",mode!=\"iowait\",mode!=\"steal\"}[5m])) by (instance)",
              "legendFormat": "{{vmi}}",
              "range": true,
              "refId": "A"
            }
          ],
          "title": "Node CPU Ultilization ",
          "type": "timeseries"
        }
      ],
      "title": "OpenShift Virtualization Overview",
      "type": "row"
    },
    {
      "collapsed": true,
      "gridPos": {
        "h": 1,
        "w": 24,
        "x": 0,
        "y": 1
      },
      "id": 56,
      "panels": [
        {
          "datasource": {
            "type": "prometheus",
            "uid": "PF55DCC5EC58ABF5A"
          },
          "fieldConfig": {
            "defaults": {
              "color": {
                "fixedColor": "super-light-green",
                "mode": "fixed"
              },
              "custom": {
                "axisCenteredZero": false,
                "axisColorMode": "text",
                "axisLabel": "",
                "axisPlacement": "auto",
                "barAlignment": 0,
                "drawStyle": "line",
                "fillOpacity": 0,
                "gradientMode": "none",
                "hideFrom": {
                  "legend": false,
                  "tooltip": false,
                  "viz": false
                },
                "lineInterpolation": "linear",
                "lineWidth": 1,
                "pointSize": 5,
                "scaleDistribution": {
                  "type": "linear"
                },
                "showPoints": "auto",
                "spanNulls": false,
                "stacking": {
                  "group": "A",
                  "mode": "none"
                },
                "thresholdsStyle": {
                  "mode": "off"
                }
              },
              "mappings": [],
              "thresholds": {
                "mode": "absolute",
                "steps": [
                  {
                    "color": "green",
                    "value": null
                  },
                  {
                    "color": "red",
                    "value": 80
                  }
                ]
              },
              "unit": "iops"
            },
            "overrides": []
          },
          "gridPos": {
            "h": 8,
            "w": 12,
            "x": 0,
            "y": 2
          },
          "id": 57,
          "options": {
            "legend": {
              "calcs": [
                "max"
              ],
              "displayMode": "table",
              "placement": "bottom",
              "showLegend": true,
              "sortBy": "Max",
              "sortDesc": false
            },
            "tooltip": {
              "mode": "single",
              "sort": "none"
            }
          },
          "targets": [
            {
              "datasource": {
                "type": "prometheus",
                "uid": "PF55DCC5EC58ABF5A"
              },
              "editorMode": "code",
              "expr": "sum(rate(kubevirt_vmi_storage_iops_read_total[60s])) by (name)",
              "legendFormat": "{{vmi}}",
              "range": true,
              "refId": "A"
            }
          ],
          "title": "VMI Read IOPS",
          "type": "timeseries"
        },
        {
          "datasource": {
            "type": "prometheus",
            "uid": "PF55DCC5EC58ABF5A"
          },
          "fieldConfig": {
            "defaults": {
              "color": {
                "fixedColor": "super-light-green",
                "mode": "fixed"
              },
              "custom": {
                "axisCenteredZero": false,
                "axisColorMode": "text",
                "axisLabel": "",
                "axisPlacement": "auto",
                "barAlignment": 0,
                "drawStyle": "line",
                "fillOpacity": 0,
                "gradientMode": "none",
                "hideFrom": {
                  "legend": false,
                  "tooltip": false,
                  "viz": false
                },
                "lineInterpolation": "linear",
                "lineWidth": 1,
                "pointSize": 5,
                "scaleDistribution": {
                  "type": "linear"
                },
                "showPoints": "auto",
                "spanNulls": false,
                "stacking": {
                  "group": "A",
                  "mode": "none"
                },
                "thresholdsStyle": {
                  "mode": "off"
                }
              },
              "mappings": [],
              "thresholds": {
                "mode": "absolute",
                "steps": [
                  {
                    "color": "green",
                    "value": null
                  },
                  {
                    "color": "red",
                    "value": 80
                  }
                ]
              },
              "unit": "iops"
            },
            "overrides": []
          },
          "gridPos": {
            "h": 8,
            "w": 12,
            "x": 12,
            "y": 2
          },
          "id": 58,
          "options": {
            "legend": {
              "calcs": [
                "max"
              ],
              "displayMode": "table",
              "placement": "bottom",
              "showLegend": true,
              "sortBy": "Max",
              "sortDesc": true
            },
            "tooltip": {
              "mode": "single",
              "sort": "none"
            }
          },
          "targets": [
            {
              "datasource": {
                "type": "prometheus",
                "uid": "PF55DCC5EC58ABF5A"
              },
              "editorMode": "code",
              "expr": " sum(rate(kubevirt_vmi_storage_iops_write_total[60s])) by (name)",
              "legendFormat": "{{vmi}}",
              "range": true,
              "refId": "A"
            }
          ],
          "title": "VMI Write IOPS",
          "type": "timeseries"
        },
        {
          "datasource": {
            "type": "prometheus",
            "uid": "PF55DCC5EC58ABF5A"
          },
          "fieldConfig": {
            "defaults": {
              "color": {
                "fixedColor": "super-light-green",
                "mode": "fixed"
              },
              "custom": {
                "axisCenteredZero": false,
                "axisColorMode": "text",
                "axisLabel": "",
                "axisPlacement": "auto",
                "barAlignment": 0,
                "drawStyle": "line",
                "fillOpacity": 0,
                "gradientMode": "none",
                "hideFrom": {
                  "legend": false,
                  "tooltip": false,
                  "viz": false
                },
                "lineInterpolation": "linear",
                "lineWidth": 1,
                "pointSize": 5,
                "scaleDistribution": {
                  "type": "linear"
                },
                "showPoints": "auto",
                "spanNulls": false,
                "stacking": {
                  "group": "A",
                  "mode": "none"
                },
                "thresholdsStyle": {
                  "mode": "off"
                }
              },
              "mappings": [],
              "thresholds": {
                "mode": "absolute",
                "steps": [
                  {
                    "color": "green",
                    "value": null
                  },
                  {
                    "color": "red",
                    "value": 80
                  }
                ]
              },
              "unit": "bytes"
            },
            "overrides": []
          },
          "gridPos": {
            "h": 8,
            "w": 12,
            "x": 0,
            "y": 10
          },
          "id": 59,
          "options": {
            "legend": {
              "calcs": [
                "max"
              ],
              "displayMode": "table",
              "placement": "bottom",
              "showLegend": true,
              "sortBy": "Max",
              "sortDesc": true
            },
            "tooltip": {
              "mode": "single",
              "sort": "none"
            }
          },
          "targets": [
            {
              "datasource": {
                "type": "prometheus",
                "uid": "PF55DCC5EC58ABF5A"
              },
              "editorMode": "code",
              "expr": "sum(rate(kubevirt_vmi_storage_read_traffic_bytes_total[60s])) by (name)",
              "legendFormat": "{{vmi}}",
              "range": true,
              "refId": "A"
            }
          ],
          "title": "VMI Storage Read Traffic",
          "type": "timeseries"
        },
        {
          "datasource": {
            "type": "prometheus",
            "uid": "PF55DCC5EC58ABF5A"
          },
          "fieldConfig": {
            "defaults": {
              "color": {
                "fixedColor": "super-light-green",
                "mode": "fixed"
              },
              "custom": {
                "axisCenteredZero": false,
                "axisColorMode": "text",
                "axisLabel": "",
                "axisPlacement": "auto",
                "barAlignment": 0,
                "drawStyle": "line",
                "fillOpacity": 0,
                "gradientMode": "none",
                "hideFrom": {
                  "legend": false,
                  "tooltip": false,
                  "viz": false
                },
                "lineInterpolation": "linear",
                "lineWidth": 1,
                "pointSize": 5,
                "scaleDistribution": {
                  "type": "linear"
                },
                "showPoints": "auto",
                "spanNulls": false,
                "stacking": {
                  "group": "A",
                  "mode": "none"
                },
                "thresholdsStyle": {
                  "mode": "off"
                }
              },
              "mappings": [],
              "thresholds": {
                "mode": "absolute",
                "steps": [
                  {
                    "color": "green",
                    "value": null
                  },
                  {
                    "color": "red",
                    "value": 80
                  }
                ]
              },
              "unit": "bytes"
            },
            "overrides": []
          },
          "gridPos": {
            "h": 8,
            "w": 12,
            "x": 12,
            "y": 10
          },
          "id": 60,
          "options": {
            "legend": {
              "calcs": [
                "max"
              ],
              "displayMode": "table",
              "placement": "bottom",
              "showLegend": true,
              "sortBy": "Max",
              "sortDesc": true
            },
            "tooltip": {
              "mode": "single",
              "sort": "none"
            }
          },
          "targets": [
            {
              "datasource": {
                "type": "prometheus",
                "uid": "PF55DCC5EC58ABF5A"
              },
              "editorMode": "code",
              "expr": "sum(rate(kubevirt_vmi_storage_write_traffic_bytes_total[60s])) by (name)",
              "legendFormat": "{{vmi}}",
              "range": true,
              "refId": "A"
            }
          ],
          "title": "VMI Storage Write Traffic",
          "type": "timeseries"
        }
      ],
      "title": "Storage",
      "type": "row"
    },
    {
      "collapsed": true,
      "gridPos": {
        "h": 1,
        "w": 24,
        "x": 0,
        "y": 2
      },
      "id": 62,
      "panels": [
        {
          "datasource": {
            "type": "prometheus",
            "uid": "PF55DCC5EC58ABF5A"
          },
          "fieldConfig": {
            "defaults": {
              "color": {
                "fixedColor": "light-green",
                "mode": "fixed"
              },
              "custom": {
                "axisCenteredZero": false,
                "axisColorMode": "text",
                "axisLabel": "",
                "axisPlacement": "auto",
                "barAlignment": 0,
                "drawStyle": "line",
                "fillOpacity": 0,
                "gradientMode": "none",
                "hideFrom": {
                  "legend": false,
                  "tooltip": false,
                  "viz": false
                },
                "lineInterpolation": "linear",
                "lineWidth": 1,
                "pointSize": 5,
                "scaleDistribution": {
                  "type": "linear"
                },
                "showPoints": "auto",
                "spanNulls": false,
                "stacking": {
                  "group": "A",
                  "mode": "none"
                },
                "thresholdsStyle": {
                  "mode": "off"
                }
              },
              "mappings": [],
              "thresholds": {
                "mode": "absolute",
                "steps": [
                  {
                    "color": "green",
                    "value": null
                  },
                  {
                    "color": "red",
                    "value": 80
                  }
                ]
              },
              "unit": "bytes"
            },
            "overrides": []
          },
          "gridPos": {
            "h": 8,
            "w": 12,
            "x": 0,
            "y": 3
          },
          "id": 63,
          "options": {
            "legend": {
              "calcs": [
                "max"
              ],
              "displayMode": "table",
              "placement": "bottom",
              "showLegend": true,
              "sortBy": "Max",
              "sortDesc": false
            },
            "tooltip": {
              "mode": "single",
              "sort": "none"
            }
          },
          "targets": [
            {
              "datasource": {
                "type": "prometheus",
                "uid": "PF55DCC5EC58ABF5A"
              },
              "editorMode": "code",
              "expr": "sum(rate(kubevirt_vmi_network_receive_bytes_total[60s])) by (name)",
              "legendFormat": "{{vmi}}",
              "range": true,
              "refId": "A"
            }
          ],
          "title": "VMI Network Traffic Recevied ",
          "type": "timeseries"
        },
        {
          "datasource": {
            "type": "prometheus",
            "uid": "PF55DCC5EC58ABF5A"
          },
          "fieldConfig": {
            "defaults": {
              "color": {
                "fixedColor": "light-green",
                "mode": "fixed"
              },
              "custom": {
                "axisCenteredZero": false,
                "axisColorMode": "text",
                "axisLabel": "",
                "axisPlacement": "auto",
                "barAlignment": 0,
                "drawStyle": "line",
                "fillOpacity": 0,
                "gradientMode": "none",
                "hideFrom": {
                  "legend": false,
                  "tooltip": false,
                  "viz": false
                },
                "lineInterpolation": "linear",
                "lineWidth": 1,
                "pointSize": 5,
                "scaleDistribution": {
                  "type": "linear"
                },
                "showPoints": "auto",
                "spanNulls": false,
                "stacking": {
                  "group": "A",
                  "mode": "none"
                },
                "thresholdsStyle": {
                  "mode": "off"
                }
              },
              "mappings": [],
              "thresholds": {
                "mode": "absolute",
                "steps": [
                  {
                    "color": "green",
                    "value": null
                  },
                  {
                    "color": "red",
                    "value": 80
                  }
                ]
              },
              "unit": "bytes"
            },
            "overrides": []
          },
          "gridPos": {
            "h": 8,
            "w": 12,
            "x": 12,
            "y": 3
          },
          "id": 64,
          "options": {
            "legend": {
              "calcs": [
                "max"
              ],
              "displayMode": "table",
              "placement": "bottom",
              "showLegend": true,
              "sortBy": "Max",
              "sortDesc": false
            },
            "tooltip": {
              "mode": "single",
              "sort": "none"
            }
          },
          "targets": [
            {
              "datasource": {
                "type": "prometheus",
                "uid": "PF55DCC5EC58ABF5A"
              },
              "editorMode": "code",
              "expr": "sum(rate(kubevirt_vmi_network_transmit_bytes_total[60s])) by (name)",
              "legendFormat": "{{vmi}}",
              "range": true,
              "refId": "A"
            }
          ],
          "title": "VMI Network Traffic Transmitted",
          "type": "timeseries"
        }
      ],
      "title": "Network",
      "type": "row"
    },
    {
      "collapsed": true,
      "gridPos": {
        "h": 1,
        "w": 24,
        "x": 0,
        "y": 3
      },
      "id": 45,
      "panels": [
        {
          "datasource": {
            "type": "prometheus",
            "uid": "PF55DCC5EC58ABF5A"
          },
          "fieldConfig": {
            "defaults": {
              "color": {
                "fixedColor": "dark-green",
                "mode": "fixed"
              },
              "mappings": [],
              "thresholds": {
                "mode": "absolute",
                "steps": [
                  {
                    "color": "green",
                    "value": null
                  },
                  {
                    "color": "red",
                    "value": 80
                  }
                ]
              }
            },
            "overrides": []
          },
          "gridPos": {
            "h": 3,
            "w": 2,
            "x": 0,
            "y": 4
          },
          "id": 47,
          "options": {
            "colorMode": "value",
            "graphMode": "none",
            "justifyMode": "auto",
            "orientation": "auto",
            "reduceOptions": {
              "calcs": [
                "lastNotNull"
              ],
              "fields": "",
              "values": false
            },
            "textMode": "auto"
          },
          "pluginVersion": "9.4.3",
          "targets": [
            {
              "datasource": {
                "type": "prometheus",
                "uid": "PF55DCC5EC58ABF5A"
              },
              "editorMode": "code",
              "expr": "sum(kubevirt_vmi_migration_succeeded)",
              "legendFormat": "__auto",
              "range": true,
              "refId": "A"
            }
          ],
          "title": "Succeeded",
          "type": "stat"
        },
        {
          "datasource": {
            "type": "prometheus",
            "uid": "PF55DCC5EC58ABF5A"
          },
          "description": "Migration in Scheduling phase",
          "fieldConfig": {
            "defaults": {
              "color": {
                "fixedColor": "dark-green",
                "mode": "fixed"
              },
              "mappings": [],
              "thresholds": {
                "mode": "absolute",
                "steps": [
                  {
                    "color": "green",
                    "value": null
                  },
                  {
                    "color": "red",
                    "value": 80
                  }
                ]
              }
            },
            "overrides": []
          },
          "gridPos": {
            "h": 3,
            "w": 2,
            "x": 2,
            "y": 4
          },
          "id": 50,
          "options": {
            "colorMode": "value",
            "graphMode": "none",
            "justifyMode": "auto",
            "orientation": "auto",
            "reduceOptions": {
              "calcs": [
                "lastNotNull"
              ],
              "fields": "",
              "values": false
            },
            "textMode": "auto"
          },
          "pluginVersion": "9.4.3",
          "targets": [
            {
              "datasource": {
                "type": "prometheus",
                "uid": "PF55DCC5EC58ABF5A"
              },
              "editorMode": "code",
              "expr": "sum(kubevirt_vmi_migrations_in_scheduling_phase)",
              "legendFormat": "__auto",
              "range": true,
              "refId": "A"
            }
          ],
          "title": "Scheduling ",
          "type": "stat"
        },
        {
          "datasource": {
            "type": "prometheus",
            "uid": "PF55DCC5EC58ABF5A"
          },
          "description": "Migration in running phase",
          "fieldConfig": {
            "defaults": {
              "color": {
                "fixedColor": "dark-green",
                "mode": "fixed"
              },
              "mappings": [],
              "thresholds": {
                "mode": "absolute",
                "steps": [
                  {
                    "color": "green",
                    "value": null
                  },
                  {
                    "color": "red",
                    "value": 80
                  }
                ]
              }
            },
            "overrides": []
          },
          "gridPos": {
            "h": 3,
            "w": 2,
            "x": 4,
            "y": 4
          },
          "id": 49,
          "options": {
            "colorMode": "value",
            "graphMode": "none",
            "justifyMode": "auto",
            "orientation": "auto",
            "reduceOptions": {
              "calcs": [
                "lastNotNull"
              ],
              "fields": "",
              "values": false
            },
            "textMode": "auto"
          },
          "pluginVersion": "9.4.3",
          "targets": [
            {
              "datasource": {
                "type": "prometheus",
                "uid": "PF55DCC5EC58ABF5A"
              },
              "editorMode": "code",
              "expr": "sum(kubevirt_vmi_migrations_in_running_phase)",
              "legendFormat": "__auto",
              "range": true,
              "refId": "A"
            }
          ],
          "title": "Running ",
          "type": "stat"
        },
        {
          "datasource": {
            "type": "prometheus",
            "uid": "PF55DCC5EC58ABF5A"
          },
          "description": "Migration in pending phase",
          "fieldConfig": {
            "defaults": {
              "color": {
                "fixedColor": "dark-green",
                "mode": "fixed"
              },
              "mappings": [],
              "thresholds": {
                "mode": "absolute",
                "steps": [
                  {
                    "color": "green",
                    "value": null
                  },
                  {
                    "color": "red",
                    "value": 80
                  }
                ]
              }
            },
            "overrides": []
          },
          "gridPos": {
            "h": 3,
            "w": 2,
            "x": 6,
            "y": 4
          },
          "id": 48,
          "options": {
            "colorMode": "value",
            "graphMode": "none",
            "justifyMode": "auto",
            "orientation": "auto",
            "reduceOptions": {
              "calcs": [
                "lastNotNull"
              ],
              "fields": "",
              "values": false
            },
            "textMode": "auto"
          },
          "pluginVersion": "9.4.3",
          "targets": [
            {
              "datasource": {
                "type": "prometheus",
                "uid": "PF55DCC5EC58ABF5A"
              },
              "editorMode": "code",
              "expr": "sum(kubevirt_vmi_migrations_in_pending_phase)",
              "legendFormat": "__auto",
              "range": true,
              "refId": "A"
            }
          ],
          "title": "Pending",
          "type": "stat"
        }
      ],
      "title": "Migration",
      "type": "row"
    }
  ],
  "refresh": "",
  "revision": 1,
  "schemaVersion": 38,
  "style": "dark",
  "tags": [],
  "templating": {
    "list": []
  },
  "time": {
    "from": "now-15m",
    "to": "now"
  },
  "timepicker": {},
  "timezone": "utc",
  "title": "OpenShift Virtualization Performance",
  "uid": "tzZtO3mNk",
  "version": 29,
  "weekStart": ""
}